scripts/__init__.py
scripts/register_hkey_aumid.py
windows_toasts/__init__.py
windows_toasts/_version.py
windows_toasts/events.py
windows_toasts/exceptions.py
windows_toasts/py.typed
windows_toasts/toast.py
windows_toasts/toast_audio.py
windows_toasts/toast_document.py
windows_toasts/toasters.py
windows_toasts/wrappers.py
windows_toasts-1.3.1.dist-info/licenses/LICENSE
windows_toasts-1.3.1.dist-info/METADATA
windows_toasts-1.3.1.dist-info/WHEEL
windows_toasts-1.3.1.dist-info/entry_points.txt
windows_toasts-1.3.1.dist-info/top_level.txt
windows_toasts-1.3.1.dist-info/RECORD
