Metadata-Version: 2.4
Name: Windows-Toasts
Version: 1.3.1
Summary: Python library used to send toast notifications on Windows machines
Home-page: https://github.com/DatGuy1/Windows-Toasts
Author: DatGuy
Author-email: datguysteam@gmail.com
Project-URL: Documentation, https://windows-toasts.readthedocs.io
Project-URL: Source, https://github.com/DatGuy1/Windows-Toasts
Classifier: Development Status :: 4 - Beta
Classifier: Programming Language :: Python :: 3
Classifier: Programming Language :: Python :: 3.9
Classifier: Programming Language :: Python :: 3.10
Classifier: Programming Language :: Python :: 3.11
Classifier: Programming Language :: Python :: 3.12
Classifier: Operating System :: Microsoft :: Windows :: Windows 10
Classifier: Operating System :: Microsoft :: Windows :: Windows 11
Requires-Python: >=3.9
License-File: LICENSE
Requires-Dist: winrt-runtime~=3.0
Requires-Dist: winrt-Windows.Data.Xml.Dom~=3.0
Requires-Dist: winrt-Windows.Foundation~=3.0
Requires-Dist: winrt-Windows.Foundation.Collections~=3.0
Requires-Dist: winrt-Windows.UI.Notifications~=3.0
Dynamic: author
Dynamic: author-email
Dynamic: classifier
Dynamic: description
Dynamic: description-content-type
Dynamic: home-page
Dynamic: license-file
Dynamic: project-url
Dynamic: requires-dist
Dynamic: requires-python
Dynamic: summary
